teller/__init__.py
teller-0.0.1.dist-info/LICENSE
teller-0.0.1.dist-info/METADATA
teller-0.0.1.dist-info/WHEEL
teller-0.0.1.dist-info/top_level.txt
teller-0.0.1.dist-info/RECORD
