Metadata-Version: 2.1
Name: teller
Version: 0.0.1
Summary: teller
Home-page: https://github.com/wrmsr/teller
Author: wrmsr
Author-email: timwilloney@gmail.com
License: UNKNOWN
Platform: UNKNOWN
Classifier: Programming Language :: Python :: 3
Classifier: License :: OSI Approved :: BSD License
Classifier: Operating System :: OS Independent
